{
  "hash": "ab235adb3d4df2fd6e12977c90361cd9",
  "result": {
    "engine": "knitr",
    "markdown": "---\ntitle: BrainWorkup Neuropsychology, LLC\nsubtitle: | \n  Clinical Neuropsychology Practice \\\n  **Joey Trampush, PhD**\ndescription: \"Founded by Joey Trampush, PhD, BrainWorkup is a neuropsychology practice based in Southern California. We specialize in state-of-the-art neurocognitive and neurobehavioral examinations for children, adolescents, and adults.\"\nhide-description: true\nsection-divs: true\nformat:\n  html:\n    page-layout: full\nimage: hero.png\nimage-width: 5em\nimage-height: 5em\ncss: index.css\nabout:\n  template: trestles\n  image-shape: rounded\nsidebar: false\ntags:\n  - neuropsychology\n  - forensic neuropsychology\n  - neuropsychological assessment\n  - ADHD\n  - learning disorders\n  - Joey Trampush\n  - brainworkup\n  - brain\n  - work-up\n  - workup\nrepo-actions: false\ntoc: false\nexecute: \n  echo: false\n  warning: false\n  message: false\n---\n\n\n## About\n\nFounded by Joey Trampush, PhD, BrainWorkup is a neuropsychology practice based\nin Southern California. We specialize in state-of-the-art neurocognitive and\nneurobehavioral examinations for children, adolescents, and adults. We are dedicated to understanding individual cognitive strengths and\nweaknesses, working collaboratively with you and your family. \n\n---\n\n## Services Tailored for Developing Minds\n\n- **Comprehensive Neurocognitive Examination:** Dive deep into understanding\nyour or your child's neurocognitive landscape and brain-based behavioral difficulties.\n\n- **Targeted Consultation and Advice:** Customized support for individuals and families, fostering optimal growth.\n\n- **Continued Care and Guidance:** We're here for the long haul, offering\nongoing assistance to adapt to your or your child's evolving needs.\n\n---\n\n## Data-Driven Assessment and Interpretation\n\nWe use the latest data analytic and data visualization tools to help us\ninterpret and make sense of all the neuropsychological and behavioral data you\nprovide throughout the evaluation to understand\nyour or your child's unique neurocognitive profile. We then translate these data\ninto actionable insights to help you and your family gain novel insights about\nyour concerns.\n\n\n\n\n\n\n\n\n\n\n\n---\n\n## Contact to Connect\n\nGet in touch with us to see how we can help you and your family with our\nclinical services.\n\n[Schedule a Consultation](docs/contact/index.qmd#online-inquiry)\n\nStay connected with the latest insights and resources:\n\n- [Subscribe to Our Blog](docs/blog/index.qmd)\n- [Follow Us on Mastodon](https://fosstodon.org/@brainworkup)\n\n",
    "supporting": [],
    "filters": [
      "rmarkdown/pagebreak.lua"
    ],
    "includes": {},
    "engineDependencies": {},
    "preserve": {},
    "postProcess": true
  }
}